motsmeles.py
motsmeles-3.3.0.dist-info/METADATA
motsmeles-3.3.0.dist-info/WHEEL
motsmeles-3.3.0.dist-info/entry_points.txt
motsmeles-3.3.0.dist-info/RECORD
