Metadata-Version: 2.1
Name: motsmeles
Version: 3.3.0
Summary: générateur de mots mêlés
License: MIT
Author: RadoTheProgrammer
Author-email: rado@arazakar.com
Requires-Python: >=3.12,<4.0
Classifier: License :: OSI Approved :: MIT License
Classifier: Programming Language :: Python :: 3
Classifier: Programming Language :: Python :: 3.12
Requires-Dist: numpy (>=1.26.4,<2.0.0)
Requires-Dist: pandas (>=2.2.1,<3.0.0)
